http_signature_client.py
http_signature_client-0.0.23.dist-info/LICENSE
http_signature_client-0.0.23.dist-info/METADATA
http_signature_client-0.0.23.dist-info/WHEEL
http_signature_client-0.0.23.dist-info/top_level.txt
http_signature_client-0.0.23.dist-info/RECORD
