Metadata-Version: 2.1
Name: http-signature-client
Version: 0.0.23
Summary: Implementation of the client side of the IETF draft "Signing HTTP Messages"
Home-page: https://github.com/michalc/python-http-signature-client
Author: Michal Charemza
Author-email: michal@charemza.name
License: UNKNOWN
Platform: UNKNOWN
Classifier: Programming Language :: Python :: 3
Classifier: License :: OSI Approved :: MIT License
Classifier: Operating System :: OS Independent
Classifier: Topic :: Internet :: WWW/HTTP
Classifier: Topic :: Security :: Cryptography
Requires-Python: >=3.6.3
